[
  {
    "name": "Upload",
    "link": "/demo-upload",
    "showSecond": false,
    "children": [
    {
      "name": "Upload1",
      "link": "demo-upload"
    },
    {
      "name": "Upload2",
      "link": "demo-upload2"
    }
  ]
  },
  {
    "name": "Form",
    "link": "/demo-form",
    "showSecond": false,
    "children": [
    {
      "name": "Form1",
      "link": "demo-form"
    },
    {
      "name": "Form2",
      "link": "demo-form2"
    }]
  },
  {
    "name": "Table",
    "link": "/demo-table",
    "showSecond": false,
    "children": [
    {
      "name": "Table1",
      "link": "demo-table"
    },
    {
      "name": "Table2",
      "link": "demo-table2"
    }]
  }
]
